tolio-0.2.5.dist-info/METADATA
tolio-0.2.5.dist-info/WHEEL
tolio-0.2.5.dist-info/license_files/LICENSE
tolio/__init__.py
tolio/tolio.cpython-37m-x86_64-linux-gnu.so
tolio-0.2.5.dist-info/RECORD
