Metadata-Version: 2.1
Name: tolio
Version: 0.2.5
Classifier: Programming Language :: Rust
Classifier: Programming Language :: Python :: Implementation :: CPython
Classifier: Programming Language :: Python :: Implementation :: PyPy
License-File: LICENSE
Summary: Tolio application rust extension
Requires-Python: >=3.7
Project-URL: repository, https://github.com/jozhw/tolio
